stream/__init__.py
stream/exceptions.py
stream/serializer.py
stream/utils.py
stream/client/__init__.py
stream/client/async_client.py
stream/client/base.py
stream/client/client.py
stream/collections/__init__.py
stream/collections/base.py
stream/collections/collections.py
stream/feed/__init__.py
stream/feed/base.py
stream/feed/feeds.py
stream/personalization/__init__.py
stream/personalization/base.py
stream/personalization/personalizations.py
stream/reactions/__init__.py
stream/reactions/base.py
stream/reactions/reaction.py
stream/users/__init__.py
stream/users/base.py
stream/users/user.py
stream_python-5.4.0.dist-info/LICENSE
stream_python-5.4.0.dist-info/METADATA
stream_python-5.4.0.dist-info/WHEEL
stream_python-5.4.0.dist-info/top_level.txt
stream_python-5.4.0.dist-info/RECORD
