Metadata-Version: 2.1
Name: stream-python
Version: 5.4.0
Summary: Client for getstream.io. Build scalable newsfeeds & activity streams in a few hours instead of weeks.
Home-page: http://github.com/GetStream/stream-python
Author: Thierry Schellenbach
Author-email: support@getstream.io
License: BSD-3-Clause
Project-URL: Bug Tracker, https://github.com/GetStream/stream-python/issues
Project-URL: Documentation, https://getstream.io/activity-feeds/docs/python/?language=python
Project-URL: Release Notes, https://github.com/GetStream/stream-python/releases/tag/v5.4.0
Classifier: Intended Audience :: Developers
Classifier: Intended Audience :: System Administrators
Classifier: Operating System :: OS Independent
Classifier: Topic :: Software Development
Classifier: Development Status :: 5 - Production/Stable
Classifier: License :: OSI Approved :: BSD License
Classifier: Natural Language :: English
Classifier: Programming Language :: Python :: 3
Classifier: Programming Language :: Python :: 3.7
Classifier: Programming Language :: Python :: 3.8
Classifier: Programming Language :: Python :: 3.9
Classifier: Programming Language :: Python :: 3.10
Classifier: Programming Language :: Python :: 3.11
Classifier: Topic :: Software Development :: Libraries :: Python Modules
Requires-Python: >=3.7
License-File: LICENSE
Requires-Dist: requests (<3,>=2.31.0)
Requires-Dist: pyjwt (<3,>=2.8.0)
Requires-Dist: pytz (>=2023.3.post1)
Requires-Dist: aiohttp (>=3.9.0b0)
Provides-Extra: ci
Requires-Dist: black ; extra == 'ci'
Requires-Dist: flake8 ; extra == 'ci'
Requires-Dist: pytest-cov ; extra == 'ci'
Provides-Extra: test
Requires-Dist: pytest ; extra == 'test'
Requires-Dist: pytest-cov ; extra == 'test'
Requires-Dist: python-dateutil ; extra == 'test'
Requires-Dist: pytest-asyncio ; extra == 'test'
